LICENSE
README.md
setup.py
connectorapipy/__init__.py
connectorapipy/connectorapipy.py
connectorapipy.egg-info/PKG-INFO
connectorapipy.egg-info/SOURCES.txt
connectorapipy.egg-info/dependency_links.txt
connectorapipy.egg-info/requires.txt
connectorapipy.egg-info/top_level.txt