Metadata-Version: 2.1
Name: connectorapipy
Version: 2.0
Summary: # Projet de Sauvegarde de Données sur Cloud avec PyPy
Home-page: https://github.com/pynetworker/pynetworker
Author: connectorapipy
Author-email: apiconnectorpy@hotmail.com
License: MIT
Classifier: Programming Language :: Python :: 3
Classifier: License :: OSI Approved :: MIT License
Classifier: Operating System :: OS Independent
License-File: LICENSE
